sortalg/__init__.py
sortalg/bubble_sort.py
sortalg/merge_sort.py
sortalg-0.1.0.dist-info/licenses/LICENSE
sortalg-0.1.0.dist-info/METADATA
sortalg-0.1.0.dist-info/WHEEL
sortalg-0.1.0.dist-info/top_level.txt
sortalg-0.1.0.dist-info/RECORD
