Metadata-Version: 2.4
Name: sortalg
Version: 0.1.0
Summary: a collection of sorting algorithms in python
Author: Morteza Salarkia
Author-email: Morteza Salarkia <msalarkia3@gmail.com>
License: MIT
Requires-Python: >=3.7
License-File: LICENSE
Dynamic: author
Dynamic: license-file
